{
    "devices": "0",
    "single_step": true,
    "unique_name": "main",
    "my_seed": 42,
    "BATCH": 16,
    "IMAGE_SIZE": 128,
    "which_data": "DVS_GESTURE_TONIC",
    "data_path": "/data2",
    "rate_coding": false,
    "lif_layer_v_init": 0.0,
    "lif_layer_v_decay": 0.25,
    "lif_layer_v_threshold": 0.720291189014991,
    "lif_layer_v_reset": 10000,
    "lif_layer_sg_width": 3.555718888923306,
    "synapse_conv_kernel_size": 3,
    "synapse_conv_stride": 1,
    "synapse_conv_padding": 1,
    "synapse_conv_trace_const1": 1,
    "synapse_conv_trace_const2": 0.0,
    "synapse_fc_trace_const1": 1,
    "synapse_fc_trace_const2": 0.0,
    "pre_trained": false,
    "convTrue_fcFalse": false,
    "cfg": [
        "M",
        "M",
        200,
        200
    ],
    "net_print": true,
    "weight_count_print": false,
    "pre_trained_path": "net_save/save_now_net_weights_main.pth",
    "learning_rate": 0.0001,
    "epoch_num": 300,
    "verbose_interval": 999999999,
    "validation_interval": 999999999,
    "tdBN_on": false,
    "BN_on": false,
    "surrogate": "hard_sigmoid",
    "gradient_verbose": false,
    "BPTT_on": false,
    "optimizer_what": "SGD",
    "scheduler_name": "no",
    "ddp_on": false,
    "nda_net": false,
    "domain_il_epoch": 0,
    "dvs_clipping": 2,
    "dvs_duration": 25000,
    "OTTT_sWS_on": false,
    "DFA_on": false,
    "OTTT_input_trace_on": false,
    "e_transport_swap": 0,
    "e_transport_swap_tr": 0,
    "e_transport_swap_coin": 1,
    "drop_rate": 0,
    "exclude_class": true,
    "merge_polarities": false,
    "denoise_on": false,
    "dvs_relative_timestep": false,
    "I_wanna_sweep_at_this_epoch": -1,
    "dvs_duration_domain": [],
    "extra_train_dataset": 0,
    "num_workers": 2,
    "chaching_on": true,
    "pin_memory": true,
    "TIME": 60,
    "current epoch": 4
}